README.txt
setup.py
src/mekk/__init__.py
src/mekk.nozbe.egg-info/PKG-INFO
src/mekk.nozbe.egg-info/SOURCES.txt
src/mekk.nozbe.egg-info/dependency_links.txt
src/mekk.nozbe.egg-info/entry_points.txt
src/mekk.nozbe.egg-info/namespace_packages.txt
src/mekk.nozbe.egg-info/not-zip-safe
src/mekk.nozbe.egg-info/requires.txt
src/mekk.nozbe.egg-info/top_level.txt
src/mekk/nozbe/__init__.py
src/mekk/nozbe/connection.py
src/mekk/nozbe/connection_keyring.py
src/mekk/nozbe/csv_writer.py
src/mekk/nozbe/json_writer.py
src/mekk/nozbe/nozbe.py
src/mekk/nozbe/run.py