Metadata-Version: 1.0
Name: mekk.nozbe
Version: 0.4.0
Summary: Nozbe interface wrapper.
Home-page: http://bitbucket.org/Mekk/mekk.nozbe/
Author: Marcin Kasperski
Author-email: Marcin.Kasperski@mekk.waw.pl
License: Artistic
Keywords: nozbe
Platform: UNKNOWN
Classifier: Programming Language :: Python
Classifier: Intended Audience :: Developers
Classifier: Topic :: Software Development :: Libraries :: Python Modules
